tinychain/__init__.py
tinychain/base.py
tinychain/chain.py
tinychain/context.py
tinychain/decorators.py
tinychain/error.py
tinychain/generic.py
tinychain/host.py
tinychain/interface.py
tinychain/json.py
tinychain/service.py
tinychain/shape.py
tinychain/state.py
tinychain/uri.py
tinychain/collection/__init__.py
tinychain/collection/base.py
tinychain/collection/btree.py
tinychain/collection/table.py
tinychain/collection/tensor/__init__.py
tinychain/collection/tensor/base.py
tinychain/collection/tensor/einsum.py
tinychain/collection/tensor/functions.py
tinychain/collection/tensor/operator.py
tinychain/graph/__init__.py
tinychain/graph/edge.py
tinychain/graph/service.py
tinychain/math/__init__.py
tinychain/math/base.py
tinychain/math/constants.py
tinychain/math/equation.py
tinychain/math/interface.py
tinychain/math/linalg.py
tinychain/math/operator.py
tinychain/ml/__init__.py
tinychain/ml/activation.py
tinychain/ml/constants.py
tinychain/ml/interface.py
tinychain/ml/nn.py
tinychain/ml/optimizer.py
tinychain/ml/service.py
tinychain/ml/variable.py
tinychain/reflect/__init__.py
tinychain/reflect/functions.py
tinychain/reflect/meta.py
tinychain/reflect/method.py
tinychain/reflect/op.py
tinychain/reflect/stub.py
tinychain/scalar/__init__.py
tinychain/scalar/base.py
tinychain/scalar/bound.py
tinychain/scalar/number.py
tinychain/scalar/op.py
tinychain/scalar/value.py
tinychain/scalar/ref/__init__.py
tinychain/scalar/ref/base.py
tinychain/scalar/ref/functions.py
tinychain-0.17.0.dist-info/METADATA
tinychain-0.17.0.dist-info/WHEEL
tinychain-0.17.0.dist-info/top_level.txt
tinychain-0.17.0.dist-info/RECORD
