Metadata-Version: 2.1
Name: tinychain
Version: 0.17.0
Summary: A Python client for TinyChain: http://git.io/JtryR
Home-page: https://github.com/haydnv/tinychain
Author: The TinyChain Contributors
Author-email: code@tinychain.net
Keywords: 'distributed cross-service transaction ml platform'
Classifier: Development Status :: 4 - Beta
Classifier: Intended Audience :: Developers
Classifier: Intended Audience :: Financial and Insurance Industry
Classifier: Intended Audience :: Information Technology
Classifier: Intended Audience :: Science/Research
Classifier: Programming Language :: Python :: 3
Classifier: License :: OSI Approved :: Apache Software License
Classifier: Operating System :: OS Independent
Classifier: Topic :: Software Development
Classifier: Topic :: Software Development :: Code Generators
Requires-Python: >=3.9
Requires-Dist: requests
